LAVASET-1.0.0.dist-info/LICENSE.txt
LAVASET-1.0.0.dist-info/RECORD
LAVASET-1.0.0.dist-info/top_level.txt
LAVASET-1.0.0.dist-info/METADATA
LAVASET-1.0.0.dist-info/WHEEL
lavaset/rf.py
lavaset/__init__.py
lavaset/cython_wrapper.cpython-311-x86_64-linux-gnu.so
lavaset/lavaboost.py
lavaset/lavaset.py
lavaset/best_cut_node.py
lavaset/gradient_boost.py
lavaset/lavaset_clifi.py
