Metadata-Version: 2.1
Name: LAVASET
Version: 1.0.0
Summary: LAVASET: Latent Variable Stochastic Ensemble of Trees. An ensemble method for correlated datasets with spatial, spectral, and temporal dependencies
Home-page: https://github.com/melkasapi/LAVASET
Author: Melpomeni Kasapi
Author-email: mk218@ic.ac.uk
Classifier: Programming Language :: Python :: 3
Classifier: License :: OSI Approved :: MIT License
Classifier: Operating System :: OS Independent
Requires-Python: >=3.9
License-File: LICENSE.txt
Requires-Dist: pandas
Requires-Dist: scikit-learn
Requires-Dist: numpy
Requires-Dist: setuptools
Requires-Dist: scipy
Requires-Dist: cython
Requires-Dist: joblib
